{
    "FACULTY OF SCIENCE": [
        {
            "course_name": "BHSci (Medical Laboratory Science)",
            "course_code": "",
            "duration": "4",
            "aps": "24",
            "required_subjects": [
                {
                    "subject": "English",
                    "level": "4",
                    "percentage": ""
                },
                {
                    "subject": "Mathematics or Technical Mathematics",
                    "level": "4",
                    "percentage": ""
                },
                {
                    "subject": "Physical Sciences or Technical Sciences",
                    "level": "4",
                    "percentage": ""
                },
                {
                    "subject": "Life Sciences",
                    "level": "4",
                    "percentage": ""
                }
            ]
        },
        {
            "course_name": "Dip (Geology)",
            "course_code": "",
            "duration": "3",
            "aps": "21",
            "required_subjects": [
                {
                    "subject": "English",
                    "level": "4",
                    "percentage": ""
                },
                {
                    "subject": "Mathematics or Technical Mathematics",
                    "level": "4",
                    "percentage": ""
                },
                {
                    "subject": "Physical Sciences or Technical Sciences",
                    "level": "4",
                    "percentage": ""
                }
            ]
        },
        {
            "course_name": "Dip (Biotechnology)",
            "course_code": "",
            "duration": "3",
            "aps": "24",
            "required_subjects": [
                {
                    "subject": "English",
                    "level": "4",
                    "percentage": ""
                },
                {
                    "subject": "Mathematics or Technical Mathematics",
                    "level": "4",
                    "percentage": ""
                },
                {
                    "subject": "Physical Sciences or Technical Sciences",
                    "level": "3",
                    "percentage": ""
                },
                {
                    "subject": "Life Sciences",
                    "level": "4",
                    "percentage": ""
                }
            ]
        },
        {
            "course_name": "Dip (Equine Science)",
            "course_code": "",
            "duration": "3",
            "aps": "19",
            "required_subjects": [
                {
                    "subject": "English",
                    "level": "4",
                    "percentage": ""
                },
                {
                    "subject": "Mathematics or Technical Mathematics",
                    "level": "3",
                    "percentage": ""
                },
                {
                    "subject": "Physical Science",
                    "level": "3",
                    "percentage": ""
                }
            ]
        },
        {
            "course_name": "Dip (Horticulture)",
            "course_code": "",
            "duration": "3",
            "aps": "25",
            "required_subjects": [
                {
                    "subject": "English",
                    "level": "4",
                    "percentage": ""
                },
                {
                    "subject": "Mathematics or Technical Mathematics or Mathematical Literacy (Level",
                    "level": "3",
                    "percentage": ""
                },
                {
                    "subject": "Life Sciences or Physical Sciences or Technical Sciences",
                    "level": "3",
                    "percentage": ""
                }
            ]
        },
        {
            "course_name": "BEnvironmental Health",
            "course_code": "",
            "duration": "4",
            "aps": "24",
            "required_subjects": [
                {
                    "subject": "English",
                    "level": "4",
                    "percentage": ""
                },
                {
                    "subject": "Mathematics or Technical Mathematics",
                    "level": "4",
                    "percentage": ""
                },
                {
                    "subject": "Physical Sciences or Technical Sciences",
                    "level": "4",
                    "percentage": ""
                },
                {
                    "subject": "Life Sciences",
                    "level": "4",
                    "percentage": ""
                },
                {
                    "subject": "Two other subjects",
                    "level": "4",
                    "percentage": ""
                }
            ]
        },
        {
            "course_name": "HCert (Resource and Waste Management)",
            "course_code": "",
            "duration": "1",
            "aps": "18",
            "required_subjects": [
                {
                    "subject": "English",
                    "level": "3",
                    "percentage": ""
                },
                {
                    "subject": "Mathematics or Technical Mathematics (Level 3) or Mathematical Literacy",
                    "level": "6",
                    "percentage": ""
                }
            ]
        },
        {
            "course_name": "BRad (Diagnostic) / Bachelor of Radiography in Diagnostics",
            "course_code": "",
            "duration": "4",
            "aps": "24",
            "required_subjects": [
                {
                    "subject": "English",
                    "level": "4",
                    "percentage": ""
                },
                {
                    "subject": "Mathematics or Technical Mathematics",
                    "level": "4",
                    "percentage": ""
                },
                {
                    "subject": "Physical Sciences or Technical Sciences",
                    "level": "4",
                    "percentage": ""
                }
            ]
        },
        {
            "course_name": "HCert (Dental Assisting)",
            "course_code": "",
            "duration": "1",
            "aps": "20",
            "required_subjects": [
                {
                    "subject": "English",
                    "level": "4",
                    "percentage": ""
                },
                {
                    "subject": "Mathematics (Level 3) or Mathematical Literacy",
                    "level": "4",
                    "percentage": ""
                },
                {
                    "subject": "Any other additional subjects",
                    "level": "3",
                    "percentage": ""
                }
            ]
        },
        {
            "course_name": "Dip (Fire Technology)",
            "course_code": "",
            "duration": "3",
            "aps": "",
            "required_subjects": [
                {
                    "subject": "A National Senior Certificate with a bachelor's degree or a diploma endorsement",
                    "level": "",
                    "percentage": ""
                },
                {
                    "subject": "an equivalent qualification",
                    "level": "",
                    "percentage": ""
                },
                {
                    "subject": "three years' relevant work experience",
                    "level": "",
                    "percentage": ""
                },
                {
                    "subject": "HAZMAT Awareness",
                    "level": "",
                    "percentage": ""
                },
                {
                    "subject": "Fire Fighter I",
                    "level": "",
                    "percentage": ""
                },
                {
                    "subject": "HAZMAT Operational",
                    "level": "",
                    "percentage": ""
                },
                {
                    "subject": "and Fire Fighter II certificates",
                    "level": "",
                    "percentage": ""
                },
                {
                    "subject": "Applicants must submit proof of employment in the form of an official letter from the employer",
                    "level": "",
                    "percentage": ""
                }
            ]
        },
        {
            "course_name": "Dip (Analytical Chemistry)",
            "course_code": "",
            "duration": "3",
            "aps": "21",
            "required_subjects": [
                {
                    "subject": "English",
                    "level": "4",
                    "percentage": ""
                },
                {
                    "subject": "Mathematics or Technical Mathematics",
                    "level": "4",
                    "percentage": ""
                },
                {
                    "subject": "Physical Sciences or Technical Sciences",
                    "level": "4",
                    "percentage": ""
                }
            ]
        },
        {
            "course_name": "Dip (Kinesiology and Coaching Science)",
            "course_code": "",
            "duration": "3",
            "aps": "24",
            "required_subjects": [
                {
                    "subject": "English",
                    "level": "3",
                    "percentage": ""
                },
                {
                    "subject": "Mathematics or Technical Mathematics or Mathematical Literacy (Level",
                    "level": "3",
                    "percentage": ""
                },
                {
                    "subject": "Life Sciences",
                    "level": "3",
                    "percentage": ""
                }
            ]
        },
        {
            "course_name": "BHSci (Clinical Technology)",
            "course_code": "",
            "duration": "4",
            "aps": "24",
            "required_subjects": [
                {
                    "subject": "English",
                    "level": "4",
                    "percentage": ""
                },
                {
                    "subject": "Mathematics or Technical Mathematics",
                    "level": "4",
                    "percentage": ""
                },
                {
                    "subject": "Physical Sciences or Technical Sciences",
                    "level": "4",
                    "percentage": ""
                },
                {
                    "subject": "Life Sciences",
                    "level": "4",
                    "percentage": ""
                }
            ]
        },
        {
            "course_name": "BHSci (Medical Orthotics and Prosthetics)",
            "course_code": "",
            "duration": "4",
            "aps": "24",
            "required_subjects": [
                {
                    "subject": "English",
                    "level": "4",
                    "percentage": ""
                },
                {
                    "subject": "Mathematics or Technical Mathematics",
                    "level": "4",
                    "percentage": ""
                },
                {
                    "subject": "Life Sciences",
                    "level": "4",
                    "percentage": ""
                },
                {
                    "subject": "Physical Sciences or Technical Sciences",
                    "level": "4",
                    "percentage": ""
                }
            ]
        },
        {
            "course_name": "Dip (Food Technology)",
            "course_code": "",
            "duration": "3",
            "aps": "24",
            "required_subjects": [
                {
                    "subject": "English",
                    "level": "4",
                    "percentage": ""
                },
                {
                    "subject": "Mathematics or Technical Mathematics",
                    "level": "4",
                    "percentage": ""
                },
                {
                    "subject": "Physical Sciences or Technical Sciences",
                    "level": "4",
                    "percentage": ""
                },
                {
                    "subject": "Life Sciences",
                    "level": "3",
                    "percentage": ""
                }
            ]
        },
        {
            "course_name": "HCert (Water Treatment)",
            "course_code": "",
            "duration": "1",
            "aps": "18",
            "required_subjects": [
                {
                    "subject": "English",
                    "level": "3",
                    "percentage": ""
                },
                {
                    "subject": "Mathematics or Technical Mathematics (Level 3) or Mathematical Literacy",
                    "level": "6",
                    "percentage": ""
                },
                {
                    "subject": "Physical Sciences or Technical Sciences",
                    "level": "3",
                    "percentage": ""
                }
            ]
        },
        {
            "course_name": "BSc (Industrial Chemistry)",
            "course_code": "",
            "duration": "4",
            "aps": "24",
            "required_subjects": [
                {
                    "subject": "English",
                    "level": "4",
                    "percentage": ""
                },
                {
                    "subject": "Mathematics",
                    "level": "5",
                    "percentage": ""
                },
                {
                    "subject": "Physical Sciences",
                    "level": "5",
                    "percentage": ""
                }
            ]
        },
        {
            "course_name": "BHSci (Biokinetics)",
            "course_code": "",
            "duration": "4",
            "aps": "24",
            "required_subjects": [
                {
                    "subject": "English",
                    "level": "4",
                    "percentage": ""
                },
                {
                    "subject": "Mathematics or Technical Mathematics",
                    "level": "4",
                    "percentage": ""
                },
                {
                    "subject": "Physical Sciences or Technical Science",
                    "level": "4",
                    "percentage": ""
                },
                {
                    "subject": "Life Sciences",
                    "level": "4",
                    "percentage": ""
                }
            ]
        },
        {
            "course_name": "Dip (Somatic Therapy)",
            "course_code": "",
            "duration": "3",
            "aps": "22",
            "required_subjects": [
                {
                    "subject": "English",
                    "level": "4",
                    "percentage": ""
                },
                {
                    "subject": "Mathematics or Technical Mathematics (Level 4) or Mathematical Literacy",
                    "level": "5",
                    "percentage": ""
                },
                {
                    "subject": "Life Sciences",
                    "level": "4",
                    "percentage": ""
                }
            ]
        },
        {
            "course_name": "Dip (Nature Conservation)",
            "course_code": "",
            "duration": "3",
            "aps": "24",
            "required_subjects": [
                {
                    "subject": "English",
                    "level": "4",
                    "percentage": ""
                },
                {
                    "subject": "Mathematics or Technical Mathematics or Mathematical Literacy (Level",
                    "level": "3",
                    "percentage": ""
                }
            ]
        },
        {
            "course_name": "Dip (Crop Production)",
            "course_code": "",
            "duration": "3",
            "aps": "19",
            "required_subjects": [
                {
                    "subject": "English",
                    "level": "4",
                    "percentage": ""
                },
                {
                    "subject": "Mathematics or Technical Mathematics (Level 3) or Mathematical Literacy",
                    "level": "4",
                    "percentage": ""
                }
            ]
        },
        {
            "course_name": "BHSci (Veterinary Technology)",
            "course_code": "",
            "duration": "4",
            "aps": "24",
            "required_subjects": [
                {
                    "subject": "English",
                    "level": "4",
                    "percentage": ""
                },
                {
                    "subject": "Mathematics or Technical Mathematics",
                    "level": "4",
                    "percentage": ""
                },
                {
                    "subject": "Physical Sciences or Technical Sciences",
                    "level": "4",
                    "percentage": ""
                },
                {
                    "subject": "Life Sciences or Agricultural Sciences",
                    "level": "4",
                    "percentage": ""
                }
            ]
        },
        {
            "course_name": "Dip (Environmental Sciences)",
            "course_code": "",
            "duration": "3",
            "aps": "24",
            "required_subjects": [
                {
                    "subject": "English",
                    "level": "4",
                    "percentage": ""
                },
                {
                    "subject": "Mathematics or Technical Mathematics",
                    "level": "4",
                    "percentage": ""
                },
                {
                    "subject": "Physical Sciences or Technical Sciences",
                    "level": "4",
                    "percentage": ""
                }
            ]
        },
        {
            "course_name": "Dip (Wildlife Management)",
            "course_code": "",
            "duration": "3",
            "aps": "24",
            "required_subjects": [
                {
                    "subject": "English",
                    "level": "4",
                    "percentage": ""
                },
                {
                    "subject": "Mathematics or Technical Mathematics or Mathematical Literacy (Level",
                    "level": "3",
                    "percentage": ""
                }
            ]
        },
        {
            "course_name": "BNursing",
            "course_code": "",
            "duration": "4",
            "aps": "27",
            "required_subjects": [
                {
                    "subject": "English",
                    "level": "4",
                    "percentage": ""
                },
                {
                    "subject": "Mathematics or Technical Mathematics",
                    "level": "4",
                    "percentage": ""
                },
                {
                    "subject": "Life Sciences",
                    "level": "4",
                    "percentage": ""
                }
            ]
        },
        {
            "course_name": "Dip (Animal Sciences)",
            "course_code": "",
            "duration": "3",
            "aps": "19",
            "required_subjects": [
                {
                    "subject": "English",
                    "level": "4",
                    "percentage": ""
                },
                {
                    "subject": "Mathematics or Technical Mathematics",
                    "level": "3",
                    "percentage": ""
                },
                {
                    "subject": "Physical Science",
                    "level": "3",
                    "percentage": ""
                }
            ]
        },
        {
            "course_name": "Dip (Industrial Physics)",
            "course_code": "",
            "duration": "3",
            "aps": "21",
            "required_subjects": [
                {
                    "subject": "English",
                    "level": "4",
                    "percentage": ""
                },
                {
                    "subject": "Mathematics or Technical Mathematics",
                    "level": "4",
                    "percentage": ""
                },
                {
                    "subject": "Physical Sciences or Technical Sciences",
                    "level": "4",
                    "percentage": ""
                }
            ]
        },
        {
            "course_name": "BPharm / Bachelor of Pharmacy",
            "course_code": "",
            "duration": "4",
            "aps": "24",
            "required_subjects": [
                {
                    "subject": "English",
                    "level": "4",
                    "percentage": ""
                },
                {
                    "subject": "Mathematics or Technical Mathematics",
                    "level": "4",
                    "percentage": ""
                },
                {
                    "subject": "Physical Sciences or Technical Sciences",
                    "level": "4",
                    "percentage": ""
                },
                {
                    "subject": "Life Sciences",
                    "level": "4",
                    "percentage": ""
                },
                {
                    "subject": "Two other subjects",
                    "level": "4",
                    "percentage": ""
                }
            ]
        },
        {
            "course_name": "Dip (Water Science and Technology)",
            "course_code": "",
            "duration": "3",
            "aps": "21",
            "required_subjects": [
                {
                    "subject": "English",
                    "level": "4",
                    "percentage": ""
                },
                {
                    "subject": "Mathematics or Technical Mathematics",
                    "level": "4",
                    "percentage": ""
                },
                {
                    "subject": "Physical Sciences or Technical Sciences",
                    "level": "4",
                    "percentage": ""
                }
            ]
        },
        {
            "course_name": "Dip (Landscape Technology)",
            "course_code": "",
            "duration": "3",
            "aps": "25",
            "required_subjects": [
                {
                    "subject": "English",
                    "level": "4",
                    "percentage": ""
                },
                {
                    "subject": "Mathematics or Technical Mathematics or Mathematical Literacy (Level",
                    "level": "3",
                    "percentage": ""
                },
                {
                    "subject": "Life Sciences or Physical Sciences or Technical Sciences",
                    "level": "3",
                    "percentage": ""
                }
            ]
        }
    ],
    "FACULTY OF ENGINEERING & THE BUILT ENVIRONMENT": [
        {
            "course_name": "HCert (Mechanical Engineering)",
            "course_code": "",
            "duration": "1",
            "aps": "20",
            "required_subjects": [
                {
                    "subject": "English",
                    "level": "4",
                    "percentage": ""
                },
                {
                    "subject": "Mathematics or Technical Mathematics",
                    "level": "4",
                    "percentage": ""
                },
                {
                    "subject": "Physical Sciences or Technical Sciences",
                    "level": "3",
                    "percentage": ""
                }
            ]
        },
        {
            "course_name": "Dip (Building Science)",
            "course_code": "",
            "duration": "3",
            "aps": "26",
            "required_subjects": [
                {
                    "subject": "English",
                    "level": "4",
                    "percentage": ""
                },
                {
                    "subject": "Mathematics or Technical Mathematics",
                    "level": "3",
                    "percentage": ""
                },
                {
                    "subject": "Physical Sciences or Technical Sciences",
                    "level": "3",
                    "percentage": ""
                }
            ]
        },
        {
            "course_name": "BEngTech (Mechatronics Engineering)",
            "course_code": "",
            "duration": "3",
            "aps": "28",
            "required_subjects": [
                {
                    "subject": "English",
                    "level": "4",
                    "percentage": ""
                },
                {
                    "subject": "Mathematics or Technical Mathematics",
                    "level": "5",
                    "percentage": ""
                },
                {
                    "subject": "Physical Sciences or Technical Sciences",
                    "level": "5",
                    "percentage": ""
                }
            ]
        },
        {
            "course_name": "HCert (Construction Engineering: Water and Waste)",
            "course_code": "",
            "duration": "1",
            "aps": "20",
            "required_subjects": [
                {
                    "subject": "English",
                    "level": "4",
                    "percentage": ""
                },
                {
                    "subject": "Mathematics or Technical Mathematics",
                    "level": "4",
                    "percentage": ""
                },
                {
                    "subject": "Physical Sciences or Technical Sciences",
                    "level": "3",
                    "percentage": ""
                }
            ]
        },
        {
            "course_name": "BEngTech (Industrial Engineering)",
            "course_code": "",
            "duration": "3",
            "aps": "28",
            "required_subjects": [
                {
                    "subject": "English",
                    "level": "4",
                    "percentage": ""
                },
                {
                    "subject": "Mathematics or Technical Mathematics",
                    "level": "5",
                    "percentage": ""
                },
                {
                    "subject": "Physical Sciences or Technical Sciences",
                    "level": "5",
                    "percentage": ""
                }
            ]
        },
        {
            "course_name": "BEngTech (Metallurgical Engineering)",
            "course_code": "",
            "duration": "3",
            "aps": "28",
            "required_subjects": [
                {
                    "subject": "English",
                    "level": "4",
                    "percentage": ""
                },
                {
                    "subject": "Mathematics or Technical Mathematics",
                    "level": "5",
                    "percentage": ""
                },
                {
                    "subject": "Physical Sciences or Technical Sciences",
                    "level": "5",
                    "percentage": ""
                }
            ]
        },
        {
            "course_name": "BEng (Materials Engineering) (Polymer Technology)",
            "course_code": "",
            "duration": "3",
            "aps": "28",
            "required_subjects": [
                {
                    "subject": "English",
                    "level": "4",
                    "percentage": ""
                },
                {
                    "subject": "Mathematics or Technical Mathematics",
                    "level": "5",
                    "percentage": ""
                },
                {
                    "subject": "Physical Sciences or Technical Sciences",
                    "level": "5",
                    "percentage": ""
                }
            ]
        },
        {
            "course_name": "Dip (Industrial Design)",
            "course_code": "",
            "duration": "3",
            "aps": "21",
            "required_subjects": [
                {
                    "subject": "English",
                    "level": "4",
                    "percentage": ""
                },
                {
                    "subject": "Mathematics or Technical Mathematics (Level 3) or Mathematical Literacy",
                    "level": "4",
                    "percentage": ""
                }
            ]
        },
        {
            "course_name": "BArch/Bachelor of Architecture",
            "course_code": "",
            "duration": "4",
            "aps": "25",
            "required_subjects": [
                {
                    "subject": "English",
                    "level": "4",
                    "percentage": ""
                },
                {
                    "subject": "Mathematics or Technical Mathematics or Mathematical Literacy",
                    "level": "4",
                    "percentage": ""
                }
            ]
        },
        {
            "course_name": "BEngTech (Chemical Engineering)",
            "course_code": "",
            "duration": "3",
            "aps": "28",
            "required_subjects": [
                {
                    "subject": "English",
                    "level": "4",
                    "percentage": ""
                },
                {
                    "subject": "Mathematics or Technical Mathematics",
                    "level": "5",
                    "percentage": ""
                },
                {
                    "subject": "Physical Sciences or Technical Sciences",
                    "level": "5",
                    "percentage": ""
                }
            ]
        },
        {
            "course_name": "HCert (Industrial Engineering)",
            "course_code": "",
            "duration": "1",
            "aps": "20",
            "required_subjects": [
                {
                    "subject": "English",
                    "level": "4",
                    "percentage": ""
                },
                {
                    "subject": "Mathematics or Technical Mathematics",
                    "level": "4",
                    "percentage": ""
                },
                {
                    "subject": "Physical Sciences or Technical Sciences",
                    "level": "3",
                    "percentage": ""
                }
            ]
        },
        {
            "course_name": "BEngTech (Civil Engineering)",
            "course_code": "",
            "duration": "3",
            "aps": "30",
            "required_subjects": [
                {
                    "subject": "English",
                    "level": "4",
                    "percentage": ""
                },
                {
                    "subject": "Mathematics or Technical Mathematics",
                    "level": "5",
                    "percentage": ""
                },
                {
                    "subject": "Physical Sciences or Technical Sciences",
                    "level": "5",
                    "percentage": ""
                }
            ]
        },
        {
            "course_name": "Dip (Civil Engineering)",
            "course_code": "",
            "duration": "3",
            "aps": "26",
            "required_subjects": [
                {
                    "subject": "English",
                    "level": "4",
                    "percentage": ""
                },
                {
                    "subject": "Mathematics or Technical Mathematics",
                    "level": "4",
                    "percentage": ""
                },
                {
                    "subject": "Physical Sciences or Technical Sciences",
                    "level": "4",
                    "percentage": ""
                }
            ]
        },
        {
            "course_name": "BEngTech (Mechanical Engineering)",
            "course_code": "",
            "duration": "3",
            "aps": "28",
            "required_subjects": [
                {
                    "subject": "English",
                    "level": "4",
                    "percentage": ""
                },
                {
                    "subject": "Mathematics or Technical Mathematics",
                    "level": "5",
                    "percentage": ""
                },
                {
                    "subject": "Physical Sciences or Technical Sciences",
                    "level": "5",
                    "percentage": ""
                }
            ]
        },
        {
            "course_name": "Dip (Electrical Engineering)",
            "course_code": "",
            "duration": "3",
            "aps": "26",
            "required_subjects": [
                {
                    "subject": "English",
                    "level": "4",
                    "percentage": ""
                },
                {
                    "subject": "Mathematics or Technical Mathematics",
                    "level": "4",
                    "percentage": ""
                },
                {
                    "subject": "Physical Sciences or Technical Sciences",
                    "level": "4",
                    "percentage": ""
                }
            ]
        },
        {
            "course_name": "BEngTech (Electrical Engineering)",
            "course_code": "",
            "duration": "3",
            "aps": "30",
            "required_subjects": [
                {
                    "subject": "English",
                    "level": "4",
                    "percentage": ""
                },
                {
                    "subject": "Mathematics or Technical Mathematics",
                    "level": "5",
                    "percentage": ""
                },
                {
                    "subject": "Physical Sciences or Technical Sciences",
                    "level": "5",
                    "percentage": ""
                },
                {
                    "subject": "Any three additional subjects",
                    "level": "4",
                    "percentage": ""
                }
            ]
        },
        {
            "course_name": "BArch/Bachelor of Architecture (Extended)",
            "course_code": "",
            "duration": "5",
            "aps": "25",
            "required_subjects": [
                {
                    "subject": "English",
                    "level": "4",
                    "percentage": ""
                },
                {
                    "subject": "Mathematics or Technical Mathematics or Mathematical Literacy",
                    "level": "4",
                    "percentage": ""
                }
            ]
        },
        {
            "course_name": "HCert (Electrical Engineering)",
            "course_code": "",
            "duration": "1",
            "aps": "20",
            "required_subjects": [
                {
                    "subject": "English",
                    "level": "4",
                    "percentage": ""
                },
                {
                    "subject": "Mathematics or Technical Mathematics",
                    "level": "4",
                    "percentage": ""
                },
                {
                    "subject": "Physical Sciences or Technical Sciences",
                    "level": "3",
                    "percentage": ""
                }
            ]
        },
        {
            "course_name": "Dip (Geomatics)",
            "course_code": "",
            "duration": "3",
            "aps": "23",
            "required_subjects": [
                {
                    "subject": "English",
                    "level": "4",
                    "percentage": ""
                },
                {
                    "subject": "Mathematics or Technical Mathematics",
                    "level": "4",
                    "percentage": ""
                },
                {
                    "subject": "Physical Sciences or Technical Sciences",
                    "level": "3",
                    "percentage": ""
                }
            ]
        },
        {
            "course_name": "HCert (Construction Engineering: Material Test)",
            "course_code": "",
            "duration": "1",
            "aps": "20",
            "required_subjects": [
                {
                    "subject": "English",
                    "level": "4",
                    "percentage": ""
                },
                {
                    "subject": "Mathematics or Technical Mathematics",
                    "level": "4",
                    "percentage": ""
                },
                {
                    "subject": "Physical Sciences or Technical Sciences",
                    "level": "3",
                    "percentage": ""
                }
            ]
        },
        {
            "course_name": "BGeomatics",
            "course_code": "",
            "duration": "3",
            "aps": "25",
            "required_subjects": [
                {
                    "subject": "English",
                    "level": "4",
                    "percentage": ""
                },
                {
                    "subject": "Mathematics or Technical Mathematics",
                    "level": "5",
                    "percentage": ""
                },
                {
                    "subject": "Physical Sciences or Technical Sciences",
                    "level": "4",
                    "percentage": ""
                }
            ]
        }
    ],
    "FACULTY OF HUMANITIES": [
        {
            "course_name": "Dip (Journalism)",
            "course_code": "",
            "duration": "3",
            "aps": "24",
            "required_subjects": [
                {
                    "subject": "English",
                    "level": "4",
                    "percentage": ""
                }
            ]
        },
        {
            "course_name": "BEd (Senior Phase and Further Education and Training Teaching) (Specialisation in Physical Education)",
            "course_code": "",
            "duration": "4",
            "aps": "24",
            "required_subjects": [
                {
                    "subject": "English",
                    "level": "4",
                    "percentage": ""
                },
                {
                    "subject": "Mathematics or Technical Mathematics or Mathematical Literacy",
                    "level": "4",
                    "percentage": ""
                },
                {
                    "subject": "Life Sciences",
                    "level": "4",
                    "percentage": ""
                }
            ]
        },
        {
            "course_name": "Dip (Public Affairs) (Admin of State)",
            "course_code": "",
            "duration": "3",
            "aps": "20",
            "required_subjects": [
                {
                    "subject": "English",
                    "level": "3",
                    "percentage": ""
                },
                {
                    "subject": "Mathematics or Mathematical Literacy",
                    "level": "3",
                    "percentage": ""
                }
            ]
        },
        {
            "course_name": "Dip (Traffic Safety and Municipal Police Management)",
            "course_code": "",
            "duration": "3",
            "aps": "",
            "required_subjects": [
                {
                    "subject": "FOR APPLICANTS WHO ARE EMPLOYED IN A LAW ENFORCEMENT DEPARTMENT: A Senior Certificate or a National Senior Certificate with a bachelor's degree or a diploma endorsement",
                    "level": "",
                    "percentage": ""
                },
                {
                    "subject": "and a relevant NQF Level 5 or 6 qualification in the law enforcement environment",
                    "level": "",
                    "percentage": ""
                },
                {
                    "subject": "Applicants are also required to have at least five (5) years of confirmed working experience as a law enforcement official",
                    "level": "",
                    "percentage": ""
                },
                {
                    "subject": "Proof of employment (in the form of an official letter from the HR division of the department) should be submitted with the application",
                    "level": "",
                    "percentage": ""
                }
            ]
        },
        {
            "course_name": "Dip (Adult and Community Education and Training) (Specialisation in Civil Technology)",
            "course_code": "",
            "duration": "3",
            "aps": "22",
            "required_subjects": [
                {
                    "subject": "English",
                    "level": "4",
                    "percentage": ""
                },
                {
                    "subject": "Engineering Graphics Design or Mathematics or Technical Mathematics",
                    "level": "3",
                    "percentage": ""
                },
                {
                    "subject": "Civil Technology or Physical Science or Technical Science",
                    "level": "3",
                    "percentage": ""
                },
                {
                    "subject": "Additional language",
                    "level": "3",
                    "percentage": ""
                }
            ]
        },
        {
            "course_name": "Dip (Policing)",
            "course_code": "",
            "duration": "3",
            "aps": "",
            "required_subjects": [
                {
                    "subject": "FOR APPLICANTS WHO ARE EMPLOYED IN A LAW ENFORCEMENT DEPARTMENT: A Senior Certificate or a National Senior Certificate with a bachelor's degree or a diploma endorsement",
                    "level": "",
                    "percentage": ""
                },
                {
                    "subject": "and a relevant NQF Level 5 or 6 qualification in the law enforcement environment",
                    "level": "",
                    "percentage": ""
                },
                {
                    "subject": "Applicants are also required to have at least five (5) years of confirmed working experience as a law enforcement official",
                    "level": "",
                    "percentage": ""
                },
                {
                    "subject": "Proof of employment (in the form of an official letter from the HR division of the department) should be submitted with the application",
                    "level": "",
                    "percentage": ""
                }
            ]
        },
        {
            "course_name": "BEd (Intermediate Phase Teaching)",
            "course_code": "",
            "duration": "4",
            "aps": "25",
            "required_subjects": [
                {
                    "subject": "English",
                    "level": "4",
                    "percentage": ""
                },
                {
                    "subject": "Any other home language offered in the programme",
                    "level": "4",
                    "percentage": ""
                },
                {
                    "subject": "Mathematics Level 4 or Mathematical Literacy",
                    "level": "5",
                    "percentage": ""
                },
                {
                    "subject": "One of the following combinations: Life Sciences",
                    "level": "",
                    "percentage": ""
                },
                {
                    "subject": "Physical Science Level 4 or History",
                    "level": "",
                    "percentage": ""
                },
                {
                    "subject": "Geography",
                    "level": "4",
                    "percentage": ""
                }
            ]
        },
        {
            "course_name": "BEd (Senior Phase and Further Education and Training Teaching) (Specialisation in Technology)",
            "course_code": "",
            "duration": "4",
            "aps": "24",
            "required_subjects": [
                {
                    "subject": "English",
                    "level": "4",
                    "percentage": ""
                },
                {
                    "subject": "Mathematics or Technical Mathematics and/or Civil Technology (Civil Service/Construction/Woodworking) and/or Electrical Technology (Digital Systems/Electronics/Power Systems) and/or Mechanical Technology (Automotive/Fitting",
                    "level": "",
                    "percentage": ""
                },
                {
                    "subject": "Machining/Welding",
                    "level": "",
                    "percentage": ""
                },
                {
                    "subject": "Metal Work) and/or Engineering Graphics",
                    "level": "",
                    "percentage": ""
                },
                {
                    "subject": "Design and/or Physical Sciences or Technical Sciences",
                    "level": "4",
                    "percentage": ""
                }
            ]
        },
        {
            "course_name": "BEd (Senior Phase and Further Education and Training Teaching) (Specialisation in Consumer Sciences)",
            "course_code": "",
            "duration": "4",
            "aps": "24",
            "required_subjects": [
                {
                    "subject": "English",
                    "level": "4",
                    "percentage": ""
                },
                {
                    "subject": "Mathematics or Technical Mathematics or Mathematical Literacy",
                    "level": "4",
                    "percentage": ""
                },
                {
                    "subject": "Consumer Studies or Hospitality Studies or Tourism",
                    "level": "4",
                    "percentage": ""
                }
            ]
        },
        {
            "course_name": "Dip (Language Practice)",
            "course_code": "",
            "duration": "3",
            "aps": "20",
            "required_subjects": [
                {
                    "subject": "English",
                    "level": "4",
                    "percentage": ""
                },
                {
                    "subject": "Any other official South African language offered in the programme",
                    "level": "5",
                    "percentage": ""
                }
            ]
        },
        {
            "course_name": "BEd (Senior Phase and Further Education and Training Teaching) (Specialisation in Mathematics)",
            "course_code": "",
            "duration": "4",
            "aps": "24",
            "required_subjects": [
                {
                    "subject": "English",
                    "level": "4",
                    "percentage": ""
                },
                {
                    "subject": "Mathematics",
                    "level": "",
                    "percentage": ""
                },
                {
                    "subject": "Life Sciences Level 4 or Mathematics",
                    "level": "",
                    "percentage": ""
                },
                {
                    "subject": "Physical Sciences",
                    "level": "4",
                    "percentage": ""
                }
            ]
        },
        {
            "course_name": "Dip (Law)",
            "course_code": "",
            "duration": "3",
            "aps": "20",
            "required_subjects": [
                {
                    "subject": "English",
                    "level": "4",
                    "percentage": ""
                }
            ]
        },
        {
            "course_name": "Dip (Correctional and Rehabilitation Studies)",
            "course_code": "",
            "duration": "3",
            "aps": "20",
            "required_subjects": [
                {
                    "subject": "English",
                    "level": "3",
                    "percentage": ""
                },
                {
                    "subject": "Mathematics or Mathematical Literacy",
                    "level": "3",
                    "percentage": ""
                }
            ]
        },
        {
            "course_name": "BEd (Senior Phase and Further Education and Training Teaching) (Specialisation in Agriculture)",
            "course_code": "",
            "duration": "4",
            "aps": "24",
            "required_subjects": [
                {
                    "subject": "English",
                    "level": "4",
                    "percentage": ""
                },
                {
                    "subject": "Mathematics or Technical Mathematics or Mathematical Literacy",
                    "level": "4",
                    "percentage": ""
                },
                {
                    "subject": "Agricultural Sciences or Life Sciences",
                    "level": "4",
                    "percentage": ""
                },
                {
                    "subject": "Agricultural Technology or Physical Sciences or Technical Sciences",
                    "level": "4",
                    "percentage": ""
                }
            ]
        },
        {
            "course_name": "BEd (Senior Phase and Further Education and Training Teaching) (Specialisation in Economic and Management Sciences)",
            "course_code": "",
            "duration": "4",
            "aps": "24",
            "required_subjects": [
                {
                    "subject": "English",
                    "level": "4",
                    "percentage": ""
                },
                {
                    "subject": "Mathematics or Technical Mathematics or Mathematical Literacy",
                    "level": "4",
                    "percentage": ""
                },
                {
                    "subject": "Accounting or Business Studies or Economics",
                    "level": "4",
                    "percentage": ""
                }
            ]
        },
        {
            "course_name": "Dip (Adult and Community Education and Training) (Specialisation in Electrical and Mechanical)",
            "course_code": "",
            "duration": "3",
            "aps": "22",
            "required_subjects": [
                {
                    "subject": "English",
                    "level": "4",
                    "percentage": ""
                },
                {
                    "subject": "Mathematics or Technical Mathematics",
                    "level": "3",
                    "percentage": ""
                },
                {
                    "subject": "Physical Science or Technical Science",
                    "level": "3",
                    "percentage": ""
                },
                {
                    "subject": "Additional language",
                    "level": "3",
                    "percentage": ""
                }
            ]
        },
        {
            "course_name": "Dip (Public Affairs) (Local Government)",
            "course_code": "",
            "duration": "3",
            "aps": "20",
            "required_subjects": [
                {
                    "subject": "English",
                    "level": "3",
                    "percentage": ""
                },
                {
                    "subject": "Mathematics or Mathematical Literacy",
                    "level": "3",
                    "percentage": ""
                }
            ]
        },
        {
            "course_name": "BEd (Senior Phase and Further Education and Training Teaching) (Specialisation in Sciences)",
            "course_code": "",
            "duration": "4",
            "aps": "24",
            "required_subjects": [
                {
                    "subject": "English",
                    "level": "4",
                    "percentage": ""
                },
                {
                    "subject": "Mathematics",
                    "level": "4",
                    "percentage": ""
                },
                {
                    "subject": "Life Sciences or Physical Sciences",
                    "level": "4",
                    "percentage": ""
                }
            ]
        },
        {
            "course_name": "BEd (Foundation Phase Teaching)",
            "course_code": "",
            "duration": "4",
            "aps": "25",
            "required_subjects": [
                {
                    "subject": "Home language offered in the programme",
                    "level": "5",
                    "percentage": ""
                },
                {
                    "subject": "First additional language",
                    "level": "4",
                    "percentage": ""
                },
                {
                    "subject": "Mathematics Level 4 or Mathematical Literacy",
                    "level": "5",
                    "percentage": ""
                }
            ]
        },
        {
            "course_name": "BEd (Senior Phase and Further Education and Training Teaching) (Specialisation in Information Technology)",
            "course_code": "",
            "duration": "4",
            "aps": "24",
            "required_subjects": [
                {
                    "subject": "English",
                    "level": "4",
                    "percentage": ""
                },
                {
                    "subject": "Mathematics or Technical Mathematics or Information Technology",
                    "level": "4",
                    "percentage": ""
                }
            ]
        },
        {
            "course_name": "Dip (Legal Support)",
            "course_code": "",
            "duration": "3",
            "aps": "20",
            "required_subjects": [
                {
                    "subject": "English",
                    "level": "4",
                    "percentage": ""
                },
                {
                    "subject": "Any other additional language",
                    "level": "3",
                    "percentage": ""
                }
            ]
        },
        {
            "course_name": "Dip (Adult and Community Education and Training) (Specialisation in Consumer Sciences)",
            "course_code": "",
            "duration": "3",
            "aps": "22",
            "required_subjects": [
                {
                    "subject": "English",
                    "level": "4",
                    "percentage": ""
                },
                {
                    "subject": "Mathematics or Technical Mathematics or Mathematical Literacy",
                    "level": "3",
                    "percentage": ""
                },
                {
                    "subject": "Additional language",
                    "level": "3",
                    "percentage": ""
                }
            ]
        },
        {
            "course_name": "Dip (Integrated Communication)",
            "course_code": "",
            "duration": "3",
            "aps": "20",
            "required_subjects": [
                {
                    "subject": "English",
                    "level": "4",
                    "percentage": ""
                },
                {
                    "subject": "Mathematics or Technical Mathematics or Engineering Mathematics N3",
                    "level": "",
                    "percentage": ""
                },
                {
                    "subject": "Mathematical Literacy",
                    "level": "4",
                    "percentage": ""
                },
                {
                    "subject": "Preference will be given to applicants with a score of 5 or more for English",
                    "level": "",
                    "percentage": ""
                }
            ]
        }
    ],
    "FACULTY OF MANAGEMENT SCIENCES": [
        {
            "course_name": "Dip (Sport Management)",
            "course_code": "",
            "duration": "3",
            "aps": "24",
            "required_subjects": [
                {
                    "subject": "English",
                    "level": "4",
                    "percentage": ""
                },
                {
                    "subject": "Mathematics or Technical Mathematics or Mathematical Literacy",
                    "level": "3",
                    "percentage": ""
                }
            ]
        },
        {
            "course_name": "Dip (Food Operations Management)",
            "course_code": "",
            "duration": "3",
            "aps": "24",
            "required_subjects": [
                {
                    "subject": "English",
                    "level": "3",
                    "percentage": ""
                },
                {
                    "subject": "Mathematics or Technical Mathematics or Mathematical Literacy",
                    "level": "3",
                    "percentage": ""
                }
            ]
        },
        {
            "course_name": "Dip (Marketing)",
            "course_code": "",
            "duration": "3",
            "aps": "24",
            "required_subjects": [
                {
                    "subject": "English",
                    "level": "4",
                    "percentage": ""
                },
                {
                    "subject": "Mathematics or Technical Mathematics or Mathematical Literacy",
                    "level": "3",
                    "percentage": ""
                }
            ]
        },
        {
            "course_name": "Dip (Operations Management)",
            "course_code": "",
            "duration": "3",
            "aps": "24",
            "required_subjects": [
                {
                    "subject": "English",
                    "level": "3",
                    "percentage": ""
                },
                {
                    "subject": "Mathematics or Technical Mathematics or Mathematical Literacy",
                    "level": "3",
                    "percentage": ""
                }
            ]
        },
        {
            "course_name": "Dip (Entrepreneurship)",
            "course_code": "",
            "duration": "3",
            "aps": "24",
            "required_subjects": [
                {
                    "subject": "English",
                    "level": "4",
                    "percentage": ""
                },
                {
                    "subject": "Mathematics or Technical Mathematics or Mathematical Literacy",
                    "level": "3",
                    "percentage": ""
                }
            ]
        },
        {
            "course_name": "Dip (Tourism Management)",
            "course_code": "",
            "duration": "3",
            "aps": "24",
            "required_subjects": [
                {
                    "subject": "English",
                    "level": "4",
                    "percentage": ""
                },
                {
                    "subject": "Mathematics or Technical Mathematics or Mathematical Literacy",
                    "level": "3",
                    "percentage": ""
                }
            ]
        },
        {
            "course_name": "Dip (Contact Centre Management)",
            "course_code": "",
            "duration": "3",
            "aps": "24",
            "required_subjects": [
                {
                    "subject": "English",
                    "level": "4",
                    "percentage": ""
                },
                {
                    "subject": "Mathematics or Technical Mathematics or Mathematical Literacy",
                    "level": "3",
                    "percentage": ""
                }
            ]
        },
        {
            "course_name": "HCert (Contact Centre Management) (Online presentation)",
            "course_code": "",
            "duration": "1",
            "aps": "20",
            "required_subjects": [
                {
                    "subject": "English",
                    "level": "3",
                    "percentage": ""
                }
            ]
        },
        {
            "course_name": "HCert (Administrative Information Management) (Online presentation)",
            "course_code": "",
            "duration": "1",
            "aps": "20",
            "required_subjects": [
                {
                    "subject": "English",
                    "level": "3",
                    "percentage": ""
                }
            ]
        },
        {
            "course_name": "Dip (Ecotourism Management) (Only Mbombela Campus)",
            "course_code": "",
            "duration": "3",
            "aps": "24",
            "required_subjects": [
                {
                    "subject": "English",
                    "level": "4",
                    "percentage": ""
                },
                {
                    "subject": "Mathematics or Technical Mathematics or Mathematical Literacy",
                    "level": "3",
                    "percentage": ""
                }
            ]
        },
        {
            "course_name": "Dip (Human Resource Management)",
            "course_code": "",
            "duration": "3",
            "aps": "24",
            "required_subjects": [
                {
                    "subject": "English",
                    "level": "4",
                    "percentage": ""
                },
                {
                    "subject": "Mathematics or Technical Mathematics or Mathematical Literacy",
                    "level": "3",
                    "percentage": ""
                }
            ]
        },
        {
            "course_name": "Dip (Credit Management)",
            "course_code": "",
            "duration": "3",
            "aps": "24",
            "required_subjects": [
                {
                    "subject": "English",
                    "level": "4",
                    "percentage": ""
                },
                {
                    "subject": "Mathematics or Technical Mathematics or Mathematical Literacy",
                    "level": "3",
                    "percentage": ""
                },
                {
                    "subject": "Accounting",
                    "level": "3",
                    "percentage": ""
                }
            ]
        },
        {
            "course_name": "Dip (Retail Business Management)",
            "course_code": "",
            "duration": "3",
            "aps": "24",
            "required_subjects": [
                {
                    "subject": "English",
                    "level": "4",
                    "percentage": ""
                },
                {
                    "subject": "Mathematics or Technical Mathematics or Mathematical Literacy",
                    "level": "3",
                    "percentage": ""
                }
            ]
        },
        {
            "course_name": "Dip (Administrative Information Management)",
            "course_code": "",
            "duration": "3",
            "aps": "24",
            "required_subjects": [
                {
                    "subject": "English",
                    "level": "4",
                    "percentage": ""
                },
                {
                    "subject": "Mathematics or Technical Mathematics or Mathematical Literacy",
                    "level": "3",
                    "percentage": ""
                }
            ]
        },
        {
            "course_name": "Dip (Supply Chain Management)",
            "course_code": "",
            "duration": "3",
            "aps": "24",
            "required_subjects": [
                {
                    "subject": "English",
                    "level": "4",
                    "percentage": ""
                },
                {
                    "subject": "Mathematics or Technical Mathematics or Mathematical Literacy",
                    "level": "3",
                    "percentage": ""
                }
            ]
        },
        {
            "course_name": "Dip (Event Management)",
            "course_code": "",
            "duration": "3",
            "aps": "24",
            "required_subjects": [
                {
                    "subject": "English",
                    "level": "4",
                    "percentage": ""
                },
                {
                    "subject": "Mathematics or Technical Mathematics or Mathematical Literacy",
                    "level": "3",
                    "percentage": ""
                }
            ]
        },
        {
            "course_name": "Dip (Casino Resort Management)",
            "course_code": "",
            "duration": "3",
            "aps": "24",
            "required_subjects": [
                {
                    "subject": "English",
                    "level": "4",
                    "percentage": ""
                },
                {
                    "subject": "Mathematics or Technical Mathematics or Mathematical Literacy",
                    "level": "3",
                    "percentage": ""
                }
            ]
        },
        {
            "course_name": "Dip (Hospitality Management)",
            "course_code": "",
            "duration": "3",
            "aps": "24",
            "required_subjects": [
                {
                    "subject": "English",
                    "level": "3",
                    "percentage": ""
                },
                {
                    "subject": "Mathematics or Technical Mathematics or Mathematical Literacy",
                    "level": "3",
                    "percentage": ""
                }
            ]
        },
        {
            "course_name": "Dip (Adventure Tourism Management) (Only Mbombela Campus)",
            "course_code": "",
            "duration": "3",
            "aps": "24",
            "required_subjects": [
                {
                    "subject": "English",
                    "level": "4",
                    "percentage": ""
                },
                {
                    "subject": "Mathematics or Technical Mathematics or Mathematical Literacy",
                    "level": "3",
                    "percentage": ""
                }
            ]
        },
        {
            "course_name": "Dip (Work Study)",
            "course_code": "",
            "duration": "3",
            "aps": "24",
            "required_subjects": [
                {
                    "subject": "English",
                    "level": "3",
                    "percentage": ""
                },
                {
                    "subject": "Mathematics or Technical Mathematics or Mathematical Literacy",
                    "level": "3",
                    "percentage": ""
                }
            ]
        }
    ],
    "FACULTY OF ICT": [
        {
            "course_name": "Dip (Multimedia Computing)",
            "course_code": "",
            "duration": "3",
            "aps": "26",
            "required_subjects": [
                {
                    "subject": "English",
                    "level": "4",
                    "percentage": ""
                },
                {
                    "subject": "Mathematics or Technical Mathematics",
                    "level": "5",
                    "percentage": ""
                },
                {
                    "subject": "Mathematical Literacy",
                    "level": "7",
                    "percentage": ""
                },
                {
                    "subject": "Information Technology",
                    "level": "",
                    "percentage": ""
                }
            ]
        },
        {
            "course_name": "Dip (Computer Systems Engineering)",
            "course_code": "",
            "duration": "3",
            "aps": "26",
            "required_subjects": [
                {
                    "subject": "English",
                    "level": "4",
                    "percentage": ""
                },
                {
                    "subject": "Mathematics or Technical Mathematics",
                    "level": "5",
                    "percentage": ""
                },
                {
                    "subject": "Physical Sciences or Technical Sciences",
                    "level": "4",
                    "percentage": ""
                }
            ]
        },
        {
            "course_name": "Dip (Computer Systems Engineering) (Extended)",
            "course_code": "",
            "duration": "4",
            "aps": "23",
            "required_subjects": [
                {
                    "subject": "English",
                    "level": "3",
                    "percentage": ""
                },
                {
                    "subject": "Mathematics or Technical Mathematics",
                    "level": "4",
                    "percentage": ""
                },
                {
                    "subject": "Physical Sciences or Technical Sciences",
                    "level": "3",
                    "percentage": ""
                }
            ]
        },
        {
            "course_name": "Dip (Computer Science) (Extended)",
            "course_code": "",
            "duration": "4",
            "aps": "23",
            "required_subjects": [
                {
                    "subject": "English",
                    "level": "3",
                    "percentage": ""
                },
                {
                    "subject": "Mathematics or Technical Mathematics",
                    "level": "4",
                    "percentage": ""
                },
                {
                    "subject": "Mathematical Literacy",
                    "level": "6",
                    "percentage": ""
                },
                {
                    "subject": "Information Technology",
                    "level": "",
                    "percentage": ""
                }
            ]
        },
        {
            "course_name": "Dip (Computer Science)",
            "course_code": "",
            "duration": "3",
            "aps": "26",
            "required_subjects": [
                {
                    "subject": "English",
                    "level": "4",
                    "percentage": ""
                },
                {
                    "subject": "Mathematics or Technical Mathematics",
                    "level": "5",
                    "percentage": ""
                },
                {
                    "subject": "Mathematical Literacy",
                    "level": "7",
                    "percentage": ""
                },
                {
                    "subject": "Information Technology",
                    "level": "",
                    "percentage": ""
                }
            ]
        },
        {
            "course_name": "Dip (Information Technology) (Extended)",
            "course_code": "",
            "duration": "4",
            "aps": "23",
            "required_subjects": [
                {
                    "subject": "English",
                    "level": "3",
                    "percentage": ""
                },
                {
                    "subject": "Mathematics or Technical Mathematics",
                    "level": "4",
                    "percentage": ""
                },
                {
                    "subject": "Mathematical Literacy",
                    "level": "6",
                    "percentage": ""
                },
                {
                    "subject": "Physical Science or Technical Science",
                    "level": "3",
                    "percentage": ""
                }
            ]
        },
        {
            "course_name": "Dip (Information Technology)",
            "course_code": "",
            "duration": "3",
            "aps": "26",
            "required_subjects": [
                {
                    "subject": "English",
                    "level": "4",
                    "percentage": ""
                },
                {
                    "subject": "Mathematics or Technical Mathematics",
                    "level": "5",
                    "percentage": ""
                },
                {
                    "subject": "Mathematical Literacy",
                    "level": "7",
                    "percentage": ""
                },
                {
                    "subject": "Physical Science or Technical Science",
                    "level": "3",
                    "percentage": ""
                }
            ]
        },
        {
            "course_name": "Dip (Informatics) (Extended)",
            "course_code": "",
            "duration": "4",
            "aps": "23",
            "required_subjects": [
                {
                    "subject": "English",
                    "level": "3",
                    "percentage": ""
                },
                {
                    "subject": "Mathematics or Technical Mathematics",
                    "level": "4",
                    "percentage": ""
                },
                {
                    "subject": "Mathematical Literacy",
                    "level": "6",
                    "percentage": ""
                }
            ]
        },
        {
            "course_name": "Dip (Informatics)",
            "course_code": "",
            "duration": "3",
            "aps": "26",
            "required_subjects": [
                {
                    "subject": "English",
                    "level": "4",
                    "percentage": ""
                },
                {
                    "subject": "Mathematics or Technical Mathematics",
                    "level": "5",
                    "percentage": ""
                },
                {
                    "subject": "Mathematical Literacy",
                    "level": "7",
                    "percentage": ""
                }
            ]
        },
        {
            "course_name": "Dip (Multimedia Computing) (Extended)",
            "course_code": "",
            "duration": "4",
            "aps": "23",
            "required_subjects": [
                {
                    "subject": "English",
                    "level": "3",
                    "percentage": ""
                },
                {
                    "subject": "Mathematics or Technical Mathematics",
                    "level": "4",
                    "percentage": ""
                },
                {
                    "subject": "Mathematical Literacy",
                    "level": "6",
                    "percentage": ""
                },
                {
                    "subject": "Information Technology",
                    "level": "",
                    "percentage": ""
                }
            ]
        }
    ],
    "FACULTY OF ARTS & DESIGN": [
        {
            "course_name": "Dip (Fine and Applied Arts)",
            "course_code": "",
            "duration": "3",
            "aps": "20",
            "required_subjects": [
                {
                    "subject": "English",
                    "level": "3",
                    "percentage": ""
                }
            ]
        },
        {
            "course_name": "Dip (Performing Arts) (Dance)",
            "course_code": "",
            "duration": "3",
            "aps": "20",
            "required_subjects": [
                {
                    "subject": "English",
                    "level": "4",
                    "percentage": ""
                }
            ]
        },
        {
            "course_name": "Dip (Fashion Design and Technology)",
            "course_code": "",
            "duration": "3",
            "aps": "20",
            "required_subjects": [
                {
                    "subject": "English",
                    "level": "3",
                    "percentage": ""
                }
            ]
        },
        {
            "course_name": "Dip (Performing Arts) (Technical Theatre and Design)",
            "course_code": "",
            "duration": "3",
            "aps": "20",
            "required_subjects": [
                {
                    "subject": "English",
                    "level": "4",
                    "percentage": ""
                }
            ]
        },
        {
            "course_name": "Dip (Jewellery Design and Manufacture)",
            "course_code": "",
            "duration": "3",
            "aps": "20",
            "required_subjects": [
                {
                    "subject": "English",
                    "level": "3",
                    "percentage": ""
                }
            ]
        },
        {
            "course_name": "Dip (Performing Arts) (Opera)",
            "course_code": "",
            "duration": "3",
            "aps": "20",
            "required_subjects": [
                {
                    "subject": "English",
                    "level": "4",
                    "percentage": ""
                }
            ]
        },
        {
            "course_name": "Dip (Performing Arts) (Jazz Music)",
            "course_code": "",
            "duration": "3",
            "aps": "20",
            "required_subjects": [
                {
                    "subject": "English",
                    "level": "4",
                    "percentage": ""
                }
            ]
        },
        {
            "course_name": "Dip (Interior Design)",
            "course_code": "",
            "duration": "3",
            "aps": "22",
            "required_subjects": [
                {
                    "subject": "English",
                    "level": "4",
                    "percentage": ""
                },
                {
                    "subject": "Civil Technology",
                    "level": "",
                    "percentage": ""
                },
                {
                    "subject": "Design Studies",
                    "level": "",
                    "percentage": ""
                },
                {
                    "subject": "Engineering Graphics",
                    "level": "",
                    "percentage": ""
                },
                {
                    "subject": "Design",
                    "level": "",
                    "percentage": ""
                },
                {
                    "subject": "and Visual Arts",
                    "level": "",
                    "percentage": ""
                }
            ]
        },
        {
            "course_name": "Dip (Performing Arts) (Theatre Arts and Performance)",
            "course_code": "",
            "duration": "3",
            "aps": "20",
            "required_subjects": [
                {
                    "subject": "English",
                    "level": "4",
                    "percentage": ""
                }
            ]
        },
        {
            "course_name": "HCert (Music)",
            "course_code": "",
            "duration": "1",
            "aps": "18",
            "required_subjects": [
                {
                    "subject": "English",
                    "level": "3",
                    "percentage": ""
                }
            ]
        },
        {
            "course_name": "Dip (Commercial Photography)",
            "course_code": "",
            "duration": "3",
            "aps": "22",
            "required_subjects": [
                {
                    "subject": "English",
                    "level": "3",
                    "percentage": ""
                }
            ]
        },
        {
            "course_name": "Dip (Motion Picture Production)",
            "course_code": "",
            "duration": "3",
            "aps": "22",
            "required_subjects": [
                {
                    "subject": "English",
                    "level": "4",
                    "percentage": ""
                }
            ]
        },
        {
            "course_name": "Dip (Integrated Communication Design)",
            "course_code": "",
            "duration": "3",
            "aps": "24",
            "required_subjects": [
                {
                    "subject": "English",
                    "level": "4",
                    "percentage": ""
                }
            ]
        }
    ],
    "FACULTY OF ECONOMICS & FINANCE": [
        {
            "course_name": "Dip (Financial Management)",
            "course_code": "",
            "duration": "3",
            "aps": "22",
            "required_subjects": [
                {
                    "subject": "English",
                    "level": "4",
                    "percentage": ""
                },
                {
                    "subject": "Accounting or Mathematics or Technical Mathematics",
                    "level": "3",
                    "percentage": ""
                },
                {
                    "subject": "Mathematical Literacy",
                    "level": "5",
                    "percentage": ""
                },
                {
                    "subject": "24 with Mathematical Literacy",
                    "level": "",
                    "percentage": ""
                }
            ]
        },
        {
            "course_name": "Dip (Accounting)",
            "course_code": "",
            "duration": "3",
            "aps": "22",
            "required_subjects": [
                {
                    "subject": "English",
                    "level": "4",
                    "percentage": ""
                },
                {
                    "subject": "Accounting or Mathematics or Technical Mathematics",
                    "level": "3",
                    "percentage": ""
                },
                {
                    "subject": "Mathematical Literacy",
                    "level": "5",
                    "percentage": ""
                },
                {
                    "subject": "24 with Mathematical Literacy",
                    "level": "",
                    "percentage": ""
                }
            ]
        },
        {
            "course_name": "Dip (Public Finance)",
            "course_code": "",
            "duration": "3",
            "aps": "22",
            "required_subjects": [
                {
                    "subject": "English",
                    "level": "4",
                    "percentage": ""
                },
                {
                    "subject": "Accounting or Mathematics or Technical Mathematics",
                    "level": "3",
                    "percentage": ""
                },
                {
                    "subject": "Mathematical Literacy",
                    "level": "5",
                    "percentage": ""
                },
                {
                    "subject": "23 with Accounting",
                    "level": "",
                    "percentage": ""
                },
                {
                    "subject": "24 with Mathematical Literacy",
                    "level": "",
                    "percentage": ""
                }
            ]
        },
        {
            "course_name": "Dip (Internal Auditing)",
            "course_code": "",
            "duration": "3",
            "aps": "22",
            "required_subjects": [
                {
                    "subject": "English",
                    "level": "4",
                    "percentage": ""
                },
                {
                    "subject": "Accounting or Mathematics or Technical Mathematics",
                    "level": "3",
                    "percentage": ""
                },
                {
                    "subject": "Mathematical Literacy",
                    "level": "5",
                    "percentage": ""
                },
                {
                    "subject": "24 with Mathematical Literacy",
                    "level": "",
                    "percentage": ""
                }
            ]
        },
        {
            "course_name": "Dip (Financial Planning)",
            "course_code": "",
            "duration": "3",
            "aps": "22",
            "required_subjects": [
                {
                    "subject": "English",
                    "level": "4",
                    "percentage": ""
                },
                {
                    "subject": "Accounting or Mathematics or Technical Mathematics",
                    "level": "3",
                    "percentage": ""
                },
                {
                    "subject": "Mathematical Literacy",
                    "level": "5",
                    "percentage": ""
                },
                {
                    "subject": "24 with Mathematical Literacy",
                    "level": "",
                    "percentage": ""
                }
            ]
        },
        {
            "course_name": "Dip (Economics)",
            "course_code": "",
            "duration": "3",
            "aps": "22",
            "required_subjects": [
                {
                    "subject": "English",
                    "level": "4",
                    "percentage": ""
                },
                {
                    "subject": "Mathematics or Technical Mathematics",
                    "level": "3",
                    "percentage": ""
                },
                {
                    "subject": "Mathematical Literacy",
                    "level": "6",
                    "percentage": ""
                },
                {
                    "subject": "24 with Mathematical Literacy",
                    "level": "",
                    "percentage": ""
                }
            ]
        },
        {
            "course_name": "HCert (Accounting)",
            "course_code": "",
            "duration": "1",
            "aps": "22",
            "required_subjects": [
                {
                    "subject": "English",
                    "level": "4",
                    "percentage": ""
                },
                {
                    "subject": "Mathematics or Technical Mathematics",
                    "level": "3",
                    "percentage": ""
                },
                {
                    "subject": "Mathematical Literacy",
                    "level": "4",
                    "percentage": ""
                },
                {
                    "subject": "23 with Mathematical Literacy",
                    "level": "",
                    "percentage": ""
                }
            ]
        }
    ]
}